<?xml version="1.0" encoding="utf-8"?>
<SoundBanksInfo Platform="Windows" BasePlatform="Windows" SchemaVersion="16" SoundBankVersion="145">
	<RootPaths>
		<ProjectRoot>../..</ProjectRoot>
		<SourceFilesRoot>../../.cache/Windows</SourceFilesRoot>
		<SoundBanksRoot>.</SoundBanksRoot>
		<ExternalSourcesInputFile></ExternalSourcesInputFile>
		<ExternalSourcesOutputRoot>.</ExternalSourcesOutputRoot>
	</RootPaths>
	<DialogueEvents/>
	<SoundBanks>
		<SoundBank Id="125802325" Type="User" Language="SFX" Hash="{E84B66D1-CCF3-F099-5D65-F954F548A190}">
			<ShortName>SFX_Button</ShortName>
			<Path>SFX_Button.bnk</Path>
			<Media>
				<File Id="378808529" Language="SFX" Streaming="false" Location="Memory">
					<ShortName>SFX_Button_Activate.wav</ShortName>
					<CachePath>SFX/SFX_Button_Activate_10C4C929.wem</CachePath>
				</File>
			</Media>
			<Events>
				<Event Id="2972650802" Name="Play_Button_Activate" DurationType="OneShot" DurationMin="0.74258333" DurationMax="0.74258333">
					<MediaRefs>
						<MediaRef Id="378808529"/>
					</MediaRefs>
				</Event>
			</Events>
		</SoundBank>
		<SoundBank Id="173969489" Type="User" Language="SFX" Hash="{1EE00365-60AA-16F8-60E3-1472EA90E393}">
			<ShortName>SFX_Key_Pickup</ShortName>
			<Path>SFX_Key_Pickup.bnk</Path>
			<Media>
				<File Id="932846478" Language="SFX" Streaming="false" Location="Memory">
					<ShortName>SFX_Key_Pickup.wav</ShortName>
					<CachePath>SFX/SFX_Key_Pickup_10C4C929.wem</CachePath>
				</File>
			</Media>
			<Events>
				<Event Id="2881789206" Name="Play_Key_Pickup" DurationType="OneShot" DurationMin="1.1076666" DurationMax="1.1076666">
					<MediaRefs>
						<MediaRef Id="932846478"/>
					</MediaRefs>
				</Event>
			</Events>
		</SoundBank>
		<SoundBank Id="973840868" Type="User" Language="SFX" Hash="{C7BBDD06-DA8E-2900-17E2-3BF4E06E6E1F}">
			<ShortName>MUS_ForestDungeon</ShortName>
			<Path>MUS_ForestDungeon.bnk</Path>
			<Media>
				<File Id="118347245" Language="SFX" Streaming="true" Location="Loose">
					<ShortName>MUS_ForestDungeon.wav</ShortName>
					<Path>Media/118347245.wem</Path>
					<CachePath>SFX/MUS_ForestDungeon_D79FB2B7.wem</CachePath>
				</File>
				<File Id="146592704" Language="SFX" Streaming="true" Location="Loose">
					<ShortName>MUS_MainTheme.wav</ShortName>
					<Path>Media/146592704.wem</Path>
					<CachePath>SFX/MUS_MainTheme_D79FB2B7.wem</CachePath>
				</File>
				<File Id="374556251" Language="SFX" Streaming="false" Location="Memory">
					<ShortName>MUS_GameOver_Jingle.wav</ShortName>
					<CachePath>SFX/MUS_GameOver_Jingle_D79FB2B7.wem</CachePath>
				</File>
				<File Id="421855728" Language="SFX" Streaming="true" Location="Loose">
					<ShortName>MUS_MainTown_Loop.wav</ShortName>
					<Path>Media/421855728.wem</Path>
					<CachePath>SFX/MUS_MainTown_Loop_D79FB2B7.wem</CachePath>
				</File>
				<File Id="440516985" Language="SFX" Streaming="true" Location="Loose">
					<ShortName>MUS_ForestBoss_Intro.wav</ShortName>
					<Path>Media/440516985.wem</Path>
					<CachePath>SFX/MUS_ForestBoss_Intro_D79FB2B7.wem</CachePath>
				</File>
				<File Id="728702870" Language="SFX" Streaming="true" Location="Loose">
					<ShortName>MUS_ForestBoss_Loop.wav</ShortName>
					<Path>Media/728702870.wem</Path>
					<CachePath>SFX/MUS_ForestBoss_Loop_D79FB2B7.wem</CachePath>
				</File>
				<File Id="919072691" Language="SFX" Streaming="true" Location="Loose">
					<ShortName>MUS_CastleEsterra.wav</ShortName>
					<Path>Media/919072691.wem</Path>
					<CachePath>SFX/MUS_CastleEsterra_D79FB2B7.wem</CachePath>
				</File>
				<File Id="937556372" Language="SFX" Streaming="true" Location="Loose">
					<ShortName>MUS_UndergroundForest_Loop.wav</ShortName>
					<Path>Media/937556372.wem</Path>
					<CachePath>SFX/MUS_UndergroundForest_Loop_D79FB2B7.wem</CachePath>
				</File>
				<File Id="976256781" Language="SFX" Streaming="true" Location="Loose">
					<ShortName>MUS_OverworldForest.wav</ShortName>
					<Path>Media/976256781.wem</Path>
					<CachePath>SFX/MUS_OverworldForest_D79FB2B7.wem</CachePath>
				</File>
			</Media>
			<Events>
				<Event Id="2194545525" Name="Play_DungeonMusic" DurationType="Infinite">
					<SwitchContainers>
						<SwitchContainer>
							<SwitchValue GroupType="State" GroupId="1106389198" Id="4293875712"/>
							<MediaRefs>
								<MediaRef Id="118347245"/>
							</MediaRefs>
						</SwitchContainer>
						<SwitchContainer>
							<SwitchValue GroupType="State" GroupId="1106389198" Id="387028970"/>
							<MediaRefs>
								<MediaRef Id="421855728"/>
							</MediaRefs>
						</SwitchContainer>
						<SwitchContainer>
							<SwitchValue GroupType="State" GroupId="1106389198" Id="1485340549"/>
							<MediaRefs>
								<MediaRef Id="146592704"/>
							</MediaRefs>
						</SwitchContainer>
						<SwitchContainer>
							<SwitchValue GroupType="State" GroupId="1106389198" Id="380412565"/>
							<MediaRefs>
								<MediaRef Id="919072691"/>
							</MediaRefs>
						</SwitchContainer>
						<SwitchContainer>
							<SwitchValue GroupType="State" GroupId="1106389198" Id="1984596375"/>
							<MediaRefs>
								<MediaRef Id="937556372"/>
							</MediaRefs>
						</SwitchContainer>
						<SwitchContainer>
							<SwitchValue GroupType="State" GroupId="1106389198" Id="2897915005"/>
							<MediaRefs>
								<MediaRef Id="374556251"/>
							</MediaRefs>
						</SwitchContainer>
						<SwitchContainer>
							<SwitchValue GroupType="State" GroupId="1106389198" Id="1906288962"/>
							<MediaRefs>
								<MediaRef Id="976256781"/>
							</MediaRefs>
						</SwitchContainer>
						<SwitchContainer>
							<SwitchValue GroupType="State" GroupId="1106389198" Id="949372955"/>
							<MediaRefs>
								<MediaRef Id="440516985"/>
								<MediaRef Id="728702870"/>
							</MediaRefs>
						</SwitchContainer>
					</SwitchContainers>
					<ActionSetState>
						<ActionSetStateEntry GroupId="1106389198" Id="4293875712" Name="Music_ForestDungeon"/>
					</ActionSetState>
				</Event>
			</Events>
			<StateGroups>
				<StateGroup Id="1106389198" Name="PlayingSong">
					<States>
						<State Id="380412565" Name="Music_CastleEsterra"/>
						<State Id="387028970" Name="Music_MainTown"/>
						<State Id="748895195" Name="None"/>
						<State Id="949372955" Name="Music_ForestDungeonBoss"/>
						<State Id="1485340549" Name="Music_MainTheme"/>
						<State Id="1906288962" Name="Music_OverworldForest"/>
						<State Id="1984596375" Name="Music_UndergroundForest"/>
						<State Id="2897915005" Name="Music_GameOver"/>
						<State Id="4293875712" Name="Music_ForestDungeon"/>
					</States>
				</StateGroup>
			</StateGroups>
		</SoundBank>
		<SoundBank Id="1125626846" Type="User" Language="SFX" Hash="{D6FCB6F0-0077-F925-46A5-AE444DA20B10}">
			<ShortName>SFX_Door_ForestDungeon_Open</ShortName>
			<Path>SFX_Door_ForestDungeon_Open.bnk</Path>
			<Media>
				<File Id="696430479" Language="SFX" Streaming="false" Location="Memory">
					<ShortName>SFX_BasicDoor_Open_01.wav</ShortName>
					<CachePath>SFX/SFX_BasicDoor_Open_01_10C4C929.wem</CachePath>
				</File>
			</Media>
			<Events>
				<Event Id="228997405" Name="Play_ForestDungeon_BasicDoor_Open" DurationType="OneShot" DurationMin="1.1047245" DurationMax="1.2595019">
					<MediaRefs>
						<MediaRef Id="696430479"/>
					</MediaRefs>
					<AuxBusRefs>
						<AuxBusRef Id="2137158287" Name="ForestDungeonVerb"/>
					</AuxBusRefs>
				</Event>
			</Events>
		</SoundBank>
		<SoundBank Id="1355168291" Type="User" Language="SFX" Hash="{83E3C7B0-D1F9-9733-BDD0-6E5049C6F440}">
			<ShortName>Init</ShortName>
			<Path>Init.bnk</Path>
			<Plugins>
				<ShareSets>
					<Plugin Id="2791153688" Name="Hall_Small" LibName="Wwise RoomVerb" LibId="7733251"/>
				</ShareSets>
				<AudioDevices>
					<Plugin Id="2317455096" Name="No_Output" LibName="No Output" LibId="11862023"/>
					<Plugin Id="3859886410" Name="System" LibName="System" LibId="11403271"/>
				</AudioDevices>
			</Plugins>
			<Busses>
				<Bus Id="85412153" Name="Ambience"/>
				<Bus Id="393239870" Name="SFX"/>
				<Bus Id="1229948536" Name="Environment"/>
				<Bus Id="2242381963" Name="Enemies"/>
				<Bus Id="3803692087" Name="Master Audio Bus"/>
				<Bus Id="3991942870" Name="Music"/>
				<Bus Id="4006243373" Name="Hopps"/>
			</Busses>
			<AuxBusses>
				<AuxBus Id="2137158287" Name="ForestDungeonVerb">
					<PluginRefs>
						<ShareSets>
							<PluginRef Id="2791153688"/>
						</ShareSets>
					</PluginRefs>
				</AuxBus>
			</AuxBusses>
			<StateGroups>
				<StateGroup Id="671786287" Name="GamePause">
					<States>
						<State Id="748895195" Name="None"/>
						<State Id="2443794319" Name="IsPaused"/>
						<State Id="2779060518" Name="NotPaused"/>
					</States>
				</StateGroup>
				<StateGroup Id="1106389198" Name="PlayingSong">
					<States>
						<State Id="380412565" Name="Music_CastleEsterra"/>
						<State Id="387028970" Name="Music_MainTown"/>
						<State Id="748895195" Name="None"/>
						<State Id="949372955" Name="Music_ForestDungeonBoss"/>
						<State Id="1485340549" Name="Music_MainTheme"/>
						<State Id="1906288962" Name="Music_OverworldForest"/>
						<State Id="1984596375" Name="Music_UndergroundForest"/>
						<State Id="2897915005" Name="Music_GameOver"/>
						<State Id="4293875712" Name="Music_ForestDungeon"/>
					</States>
				</StateGroup>
				<StateGroup Id="1606972574" Name="ForestDungeonStates">
					<States>
						<State Id="748895195" Name="None"/>
						<State Id="1017222595" Name="LowHealth"/>
						<State Id="1823678183" Name="Exploring"/>
						<State Id="2764240573" Name="Combat"/>
					</States>
				</StateGroup>
			</StateGroups>
			<SwitchGroups>
				<SwitchGroup Id="2116499235" Name="Footstep_SwitchGroup">
					<Switches>
						<Switch Id="1216965916" Name="Stone"/>
					</Switches>
				</SwitchGroup>
			</SwitchGroups>
		</SoundBank>
		<SoundBank Id="1817562479" Type="User" Language="SFX" Hash="{53F1E4B0-C135-2448-7F12-82F35645B0F6}">
			<ShortName>GameOver_Soundbank</ShortName>
			<Path>GameOver_Soundbank.bnk</Path>
			<Events>
				<Event Id="3458381909" Name="Play_GameOverJingle" MaxAttenuation="0" DurationType="OneShot" DurationMin="0" DurationMax="0">
					<ActionSetState>
						<ActionSetStateEntry GroupId="1106389198" Id="2897915005" Name="Music_GameOver"/>
					</ActionSetState>
				</Event>
			</Events>
			<StateGroups>
				<StateGroup Id="1106389198" Name="PlayingSong">
					<States>
						<State Id="380412565" Name="Music_CastleEsterra"/>
						<State Id="387028970" Name="Music_MainTown"/>
						<State Id="748895195" Name="None"/>
						<State Id="949372955" Name="Music_ForestDungeonBoss"/>
						<State Id="1485340549" Name="Music_MainTheme"/>
						<State Id="1906288962" Name="Music_OverworldForest"/>
						<State Id="1984596375" Name="Music_UndergroundForest"/>
						<State Id="2897915005" Name="Music_GameOver"/>
						<State Id="4293875712" Name="Music_ForestDungeon"/>
					</States>
				</StateGroup>
			</StateGroups>
		</SoundBank>
		<SoundBank Id="1922392942" Type="User" Language="SFX" Hash="{1375C765-E8F9-B49C-A958-9C6A5841B674}">
			<ShortName>MUS_MainTown</ShortName>
			<Path>MUS_MainTown.bnk</Path>
			<Media>
				<File Id="118347245" Language="SFX" Streaming="true" Location="Loose">
					<ShortName>MUS_ForestDungeon.wav</ShortName>
					<Path>Media/118347245.wem</Path>
					<CachePath>SFX/MUS_ForestDungeon_D79FB2B7.wem</CachePath>
				</File>
				<File Id="146592704" Language="SFX" Streaming="true" Location="Loose">
					<ShortName>MUS_MainTheme.wav</ShortName>
					<Path>Media/146592704.wem</Path>
					<CachePath>SFX/MUS_MainTheme_D79FB2B7.wem</CachePath>
				</File>
				<File Id="374556251" Language="SFX" Streaming="false" Location="Memory">
					<ShortName>MUS_GameOver_Jingle.wav</ShortName>
					<CachePath>SFX/MUS_GameOver_Jingle_D79FB2B7.wem</CachePath>
				</File>
				<File Id="421855728" Language="SFX" Streaming="true" Location="Loose">
					<ShortName>MUS_MainTown_Loop.wav</ShortName>
					<Path>Media/421855728.wem</Path>
					<CachePath>SFX/MUS_MainTown_Loop_D79FB2B7.wem</CachePath>
				</File>
				<File Id="440516985" Language="SFX" Streaming="true" Location="Loose">
					<ShortName>MUS_ForestBoss_Intro.wav</ShortName>
					<Path>Media/440516985.wem</Path>
					<CachePath>SFX/MUS_ForestBoss_Intro_D79FB2B7.wem</CachePath>
				</File>
				<File Id="728702870" Language="SFX" Streaming="true" Location="Loose">
					<ShortName>MUS_ForestBoss_Loop.wav</ShortName>
					<Path>Media/728702870.wem</Path>
					<CachePath>SFX/MUS_ForestBoss_Loop_D79FB2B7.wem</CachePath>
				</File>
				<File Id="919072691" Language="SFX" Streaming="true" Location="Loose">
					<ShortName>MUS_CastleEsterra.wav</ShortName>
					<Path>Media/919072691.wem</Path>
					<CachePath>SFX/MUS_CastleEsterra_D79FB2B7.wem</CachePath>
				</File>
				<File Id="937556372" Language="SFX" Streaming="true" Location="Loose">
					<ShortName>MUS_UndergroundForest_Loop.wav</ShortName>
					<Path>Media/937556372.wem</Path>
					<CachePath>SFX/MUS_UndergroundForest_Loop_D79FB2B7.wem</CachePath>
				</File>
				<File Id="976256781" Language="SFX" Streaming="true" Location="Loose">
					<ShortName>MUS_OverworldForest.wav</ShortName>
					<Path>Media/976256781.wem</Path>
					<CachePath>SFX/MUS_OverworldForest_D79FB2B7.wem</CachePath>
				</File>
			</Media>
			<Events>
				<Event Id="1134137730" Name="Play_MainTownMusic" DurationType="Infinite">
					<SwitchContainers>
						<SwitchContainer>
							<SwitchValue GroupType="State" GroupId="1106389198" Id="4293875712"/>
							<MediaRefs>
								<MediaRef Id="118347245"/>
							</MediaRefs>
						</SwitchContainer>
						<SwitchContainer>
							<SwitchValue GroupType="State" GroupId="1106389198" Id="387028970"/>
							<MediaRefs>
								<MediaRef Id="421855728"/>
							</MediaRefs>
						</SwitchContainer>
						<SwitchContainer>
							<SwitchValue GroupType="State" GroupId="1106389198" Id="1485340549"/>
							<MediaRefs>
								<MediaRef Id="146592704"/>
							</MediaRefs>
						</SwitchContainer>
						<SwitchContainer>
							<SwitchValue GroupType="State" GroupId="1106389198" Id="380412565"/>
							<MediaRefs>
								<MediaRef Id="919072691"/>
							</MediaRefs>
						</SwitchContainer>
						<SwitchContainer>
							<SwitchValue GroupType="State" GroupId="1106389198" Id="1984596375"/>
							<MediaRefs>
								<MediaRef Id="937556372"/>
							</MediaRefs>
						</SwitchContainer>
						<SwitchContainer>
							<SwitchValue GroupType="State" GroupId="1106389198" Id="2897915005"/>
							<MediaRefs>
								<MediaRef Id="374556251"/>
							</MediaRefs>
						</SwitchContainer>
						<SwitchContainer>
							<SwitchValue GroupType="State" GroupId="1106389198" Id="1906288962"/>
							<MediaRefs>
								<MediaRef Id="976256781"/>
							</MediaRefs>
						</SwitchContainer>
						<SwitchContainer>
							<SwitchValue GroupType="State" GroupId="1106389198" Id="949372955"/>
							<MediaRefs>
								<MediaRef Id="440516985"/>
								<MediaRef Id="728702870"/>
							</MediaRefs>
						</SwitchContainer>
					</SwitchContainers>
					<ActionSetState>
						<ActionSetStateEntry GroupId="1106389198" Id="387028970" Name="Music_MainTown"/>
					</ActionSetState>
				</Event>
			</Events>
			<StateGroups>
				<StateGroup Id="1106389198" Name="PlayingSong">
					<States>
						<State Id="380412565" Name="Music_CastleEsterra"/>
						<State Id="387028970" Name="Music_MainTown"/>
						<State Id="748895195" Name="None"/>
						<State Id="949372955" Name="Music_ForestDungeonBoss"/>
						<State Id="1485340549" Name="Music_MainTheme"/>
						<State Id="1906288962" Name="Music_OverworldForest"/>
						<State Id="1984596375" Name="Music_UndergroundForest"/>
						<State Id="2897915005" Name="Music_GameOver"/>
						<State Id="4293875712" Name="Music_ForestDungeon"/>
					</States>
				</StateGroup>
			</StateGroups>
		</SoundBank>
		<SoundBank Id="1996464746" Type="User" Language="SFX" Hash="{7446BA4B-AF26-70D0-1591-76F97F8C2C8C}">
			<ShortName>AMB_UndergroundForest</ShortName>
			<Path>AMB_UndergroundForest.bnk</Path>
			<Media>
				<File Id="33574240" Language="SFX" Streaming="false" Location="Memory">
					<ShortName>AMB_UndergroundForest.wav</ShortName>
					<CachePath>SFX/AMB_UndergroundForest_C682475C.wem</CachePath>
				</File>
			</Media>
			<Events>
				<Event Id="2352500859" Name="Play_UndergroundForest_AMB" DurationType="Infinite">
					<MediaRefs>
						<MediaRef Id="33574240"/>
					</MediaRefs>
				</Event>
			</Events>
		</SoundBank>
		<SoundBank Id="2197452935" Type="User" Language="SFX" Hash="{A42DFAD5-FC35-E5A4-BC67-2B741770F7F5}">
			<ShortName>Hopps_SoundBank</ShortName>
			<Path>Hopps_SoundBank.bnk</Path>
			<Media>
				<File Id="73418470" Language="SFX" Streaming="false" Location="Memory">
					<ShortName>SFX_Footstep_Stone_05.wav</ShortName>
					<CachePath>SFX/SFX_Footstep_Stone_05_10C4C929.wem</CachePath>
				</File>
				<File Id="104382167" Language="SFX" Streaming="false" Location="Memory">
					<ShortName>SFX_Hopps_Dash_Start.wav</ShortName>
					<CachePath>SFX/SFX_Hopps_Dash_Start_5DB7E025.wem</CachePath>
				</File>
				<File Id="186922672" Language="SFX" Streaming="false" Location="Memory">
					<ShortName>SFX_Footstep_Stone_03.wav</ShortName>
					<CachePath>SFX/SFX_Footstep_Stone_03_10C4C929.wem</CachePath>
				</File>
				<File Id="212019886" Language="SFX" Streaming="false" Location="Memory">
					<ShortName>SFX_Footstep_Stone_02.wav</ShortName>
					<CachePath>SFX/SFX_Footstep_Stone_02_10C4C929.wem</CachePath>
				</File>
				<File Id="316000514" Language="SFX" Streaming="false" Location="Memory">
					<ShortName>SFX_Footstep_Stone_04.wav</ShortName>
					<CachePath>SFX/SFX_Footstep_Stone_04_10C4C929.wem</CachePath>
				</File>
				<File Id="551114336" Language="SFX" Streaming="false" Location="Memory">
					<ShortName>SFX_Hopps_DamageTaken_03.wav</ShortName>
					<CachePath>SFX/SFX_Hopps_DamageTaken_03_10C4C929.wem</CachePath>
				</File>
				<File Id="623794331" Language="SFX" Streaming="false" Location="Memory">
					<ShortName>SFX_Jump_Stone_02.wav</ShortName>
					<CachePath>SFX/SFX_Jump_Stone_02_10C4C929.wem</CachePath>
				</File>
				<File Id="656144537" Language="SFX" Streaming="false" Location="Memory">
					<ShortName>SFX_Hopps_HeavyAttack_01.wav</ShortName>
					<CachePath>SFX/SFX_Hopps_HeavyAttack_01_10C4C929.wem</CachePath>
				</File>
				<File Id="885180894" Language="SFX" Streaming="false" Location="Memory">
					<ShortName>SFX_Potion_Drink_01.wav</ShortName>
					<CachePath>SFX/SFX_Potion_Drink_01_10C4C929.wem</CachePath>
				</File>
				<File Id="905258165" Language="SFX" Streaming="false" Location="Memory">
					<ShortName>SFX_Hopps_BasicAttack_01.wav</ShortName>
					<CachePath>SFX/SFX_Hopps_BasicAttack_01_10C4C929.wem</CachePath>
				</File>
				<File Id="911667991" Language="SFX" Streaming="false" Location="Memory">
					<ShortName>SFX_Jump_Stone_01.wav</ShortName>
					<CachePath>SFX/SFX_Jump_Stone_01_10C4C929.wem</CachePath>
				</File>
				<File Id="954843541" Language="SFX" Streaming="false" Location="Memory">
					<ShortName>SFX_Footstep_Stone_01.wav</ShortName>
					<CachePath>SFX/SFX_Footstep_Stone_01_10C4C929.wem</CachePath>
				</File>
				<File Id="991292264" Language="SFX" Streaming="false" Location="Memory">
					<ShortName>SFX_Hopps_DamageTaken_01.wav</ShortName>
					<CachePath>SFX/SFX_Hopps_DamageTaken_01_10C4C929.wem</CachePath>
				</File>
				<File Id="1006607113" Language="SFX" Streaming="false" Location="Memory">
					<ShortName>SFX_Hopps_DamageTaken_02.wav</ShortName>
					<CachePath>SFX/SFX_Hopps_DamageTaken_02_10C4C929.wem</CachePath>
				</File>
			</Media>
			<Events>
				<Event Id="3363411656" Name="Play_Drink_HealthPotion" DurationType="OneShot" DurationMin="1.6336666" DurationMax="1.6336666">
					<MediaRefs>
						<MediaRef Id="885180894"/>
					</MediaRefs>
				</Event>
				<Event Id="536851419" Name="Play_Hopps_BasicAttack" DurationType="OneShot" DurationMin="0.6291399" DurationMax="0.8065222">
					<MediaRefs>
						<MediaRef Id="905258165"/>
					</MediaRefs>
					<AuxBusRefs>
						<AuxBusRef Id="2137158287" Name="ForestDungeonVerb"/>
					</AuxBusRefs>
				</Event>
				<Event Id="3376665689" Name="Play_Hopps_DamageTaken" DurationType="OneShot" DurationMin="0.70090526" DurationMax="0.78673965">
					<MediaRefs>
						<MediaRef Id="551114336"/>
						<MediaRef Id="991292264"/>
						<MediaRef Id="1006607113"/>
					</MediaRefs>
				</Event>
				<Event Id="739488027" Name="Play_Hopps_Dash" DurationType="OneShot" DurationMin="1.621625" DurationMax="1.621625">
					<MediaRefs>
						<MediaRef Id="104382167"/>
					</MediaRefs>
				</Event>
				<Event Id="109051115" Name="Play_Hopps_Jump" DurationType="OneShot" DurationMin="0.44312614" DurationMax="0.56960493">
					<SwitchContainers>
						<SwitchContainer>
							<SwitchValue GroupType="Switch" GroupId="2116499235" Id="1216965916" Default="true"/>
							<MediaRefs>
								<MediaRef Id="623794331"/>
								<MediaRef Id="911667991"/>
							</MediaRefs>
						</SwitchContainer>
					</SwitchContainers>
				</Event>
				<Event Id="3862148652" Name="Play_Hopps_Walk" DurationType="OneShot" DurationMin="0.054727584" DurationMax="0.12220977">
					<SwitchContainers>
						<SwitchContainer>
							<SwitchValue GroupType="Switch" GroupId="2116499235" Id="1216965916" Default="true"/>
							<MediaRefs>
								<MediaRef Id="73418470"/>
								<MediaRef Id="186922672"/>
								<MediaRef Id="212019886"/>
								<MediaRef Id="316000514"/>
								<MediaRef Id="954843541"/>
							</MediaRefs>
						</SwitchContainer>
					</SwitchContainers>
				</Event>
				<Event Id="190067705" Name="Play_HoppsHeavyAttack" DurationType="OneShot" DurationMin="0.55182624" DurationMax="0.7718823">
					<MediaRefs>
						<MediaRef Id="656144537"/>
					</MediaRefs>
					<AuxBusRefs>
						<AuxBusRef Id="2137158287" Name="ForestDungeonVerb"/>
					</AuxBusRefs>
				</Event>
			</Events>
			<SwitchGroups>
				<SwitchGroup Id="2116499235" Name="Footstep_SwitchGroup">
					<Switches>
						<Switch Id="1216965916" Name="Stone"/>
					</Switches>
				</SwitchGroup>
			</SwitchGroups>
		</SoundBank>
		<SoundBank Id="2286727387" Type="User" Language="SFX" Hash="{351390B8-90E6-096D-3B5A-639D68EB93AF}">
			<ShortName>MUS_UndergroundForest</ShortName>
			<Path>MUS_UndergroundForest.bnk</Path>
			<Media>
				<File Id="118347245" Language="SFX" Streaming="true" Location="Loose">
					<ShortName>MUS_ForestDungeon.wav</ShortName>
					<Path>Media/118347245.wem</Path>
					<CachePath>SFX/MUS_ForestDungeon_D79FB2B7.wem</CachePath>
				</File>
				<File Id="146592704" Language="SFX" Streaming="true" Location="Loose">
					<ShortName>MUS_MainTheme.wav</ShortName>
					<Path>Media/146592704.wem</Path>
					<CachePath>SFX/MUS_MainTheme_D79FB2B7.wem</CachePath>
				</File>
				<File Id="374556251" Language="SFX" Streaming="false" Location="Memory">
					<ShortName>MUS_GameOver_Jingle.wav</ShortName>
					<CachePath>SFX/MUS_GameOver_Jingle_D79FB2B7.wem</CachePath>
				</File>
				<File Id="421855728" Language="SFX" Streaming="true" Location="Loose">
					<ShortName>MUS_MainTown_Loop.wav</ShortName>
					<Path>Media/421855728.wem</Path>
					<CachePath>SFX/MUS_MainTown_Loop_D79FB2B7.wem</CachePath>
				</File>
				<File Id="440516985" Language="SFX" Streaming="true" Location="Loose">
					<ShortName>MUS_ForestBoss_Intro.wav</ShortName>
					<Path>Media/440516985.wem</Path>
					<CachePath>SFX/MUS_ForestBoss_Intro_D79FB2B7.wem</CachePath>
				</File>
				<File Id="728702870" Language="SFX" Streaming="true" Location="Loose">
					<ShortName>MUS_ForestBoss_Loop.wav</ShortName>
					<Path>Media/728702870.wem</Path>
					<CachePath>SFX/MUS_ForestBoss_Loop_D79FB2B7.wem</CachePath>
				</File>
				<File Id="919072691" Language="SFX" Streaming="true" Location="Loose">
					<ShortName>MUS_CastleEsterra.wav</ShortName>
					<Path>Media/919072691.wem</Path>
					<CachePath>SFX/MUS_CastleEsterra_D79FB2B7.wem</CachePath>
				</File>
				<File Id="937556372" Language="SFX" Streaming="true" Location="Loose">
					<ShortName>MUS_UndergroundForest_Loop.wav</ShortName>
					<Path>Media/937556372.wem</Path>
					<CachePath>SFX/MUS_UndergroundForest_Loop_D79FB2B7.wem</CachePath>
				</File>
				<File Id="976256781" Language="SFX" Streaming="true" Location="Loose">
					<ShortName>MUS_OverworldForest.wav</ShortName>
					<Path>Media/976256781.wem</Path>
					<CachePath>SFX/MUS_OverworldForest_D79FB2B7.wem</CachePath>
				</File>
			</Media>
			<Events>
				<Event Id="1277548847" Name="Play_UndergroundForestMusic" DurationType="Infinite">
					<SwitchContainers>
						<SwitchContainer>
							<SwitchValue GroupType="State" GroupId="1106389198" Id="4293875712"/>
							<MediaRefs>
								<MediaRef Id="118347245"/>
							</MediaRefs>
						</SwitchContainer>
						<SwitchContainer>
							<SwitchValue GroupType="State" GroupId="1106389198" Id="387028970"/>
							<MediaRefs>
								<MediaRef Id="421855728"/>
							</MediaRefs>
						</SwitchContainer>
						<SwitchContainer>
							<SwitchValue GroupType="State" GroupId="1106389198" Id="1485340549"/>
							<MediaRefs>
								<MediaRef Id="146592704"/>
							</MediaRefs>
						</SwitchContainer>
						<SwitchContainer>
							<SwitchValue GroupType="State" GroupId="1106389198" Id="380412565"/>
							<MediaRefs>
								<MediaRef Id="919072691"/>
							</MediaRefs>
						</SwitchContainer>
						<SwitchContainer>
							<SwitchValue GroupType="State" GroupId="1106389198" Id="1984596375"/>
							<MediaRefs>
								<MediaRef Id="937556372"/>
							</MediaRefs>
						</SwitchContainer>
						<SwitchContainer>
							<SwitchValue GroupType="State" GroupId="1106389198" Id="2897915005"/>
							<MediaRefs>
								<MediaRef Id="374556251"/>
							</MediaRefs>
						</SwitchContainer>
						<SwitchContainer>
							<SwitchValue GroupType="State" GroupId="1106389198" Id="1906288962"/>
							<MediaRefs>
								<MediaRef Id="976256781"/>
							</MediaRefs>
						</SwitchContainer>
						<SwitchContainer>
							<SwitchValue GroupType="State" GroupId="1106389198" Id="949372955"/>
							<MediaRefs>
								<MediaRef Id="440516985"/>
								<MediaRef Id="728702870"/>
							</MediaRefs>
						</SwitchContainer>
					</SwitchContainers>
					<ActionSetState>
						<ActionSetStateEntry GroupId="1106389198" Id="1984596375" Name="Music_UndergroundForest"/>
					</ActionSetState>
				</Event>
			</Events>
			<StateGroups>
				<StateGroup Id="1106389198" Name="PlayingSong">
					<States>
						<State Id="380412565" Name="Music_CastleEsterra"/>
						<State Id="387028970" Name="Music_MainTown"/>
						<State Id="748895195" Name="None"/>
						<State Id="949372955" Name="Music_ForestDungeonBoss"/>
						<State Id="1485340549" Name="Music_MainTheme"/>
						<State Id="1906288962" Name="Music_OverworldForest"/>
						<State Id="1984596375" Name="Music_UndergroundForest"/>
						<State Id="2897915005" Name="Music_GameOver"/>
						<State Id="4293875712" Name="Music_ForestDungeon"/>
					</States>
				</StateGroup>
			</StateGroups>
		</SoundBank>
		<SoundBank Id="2546705169" Type="User" Language="SFX" Hash="{16A4EAB5-3718-C9C7-E457-FD5424BCB0B1}">
			<ShortName>MUS_CastleEsterra</ShortName>
			<Path>MUS_CastleEsterra.bnk</Path>
			<Media>
				<File Id="118347245" Language="SFX" Streaming="true" Location="Loose">
					<ShortName>MUS_ForestDungeon.wav</ShortName>
					<Path>Media/118347245.wem</Path>
					<CachePath>SFX/MUS_ForestDungeon_D79FB2B7.wem</CachePath>
				</File>
				<File Id="146592704" Language="SFX" Streaming="true" Location="Loose">
					<ShortName>MUS_MainTheme.wav</ShortName>
					<Path>Media/146592704.wem</Path>
					<CachePath>SFX/MUS_MainTheme_D79FB2B7.wem</CachePath>
				</File>
				<File Id="374556251" Language="SFX" Streaming="false" Location="Memory">
					<ShortName>MUS_GameOver_Jingle.wav</ShortName>
					<CachePath>SFX/MUS_GameOver_Jingle_D79FB2B7.wem</CachePath>
				</File>
				<File Id="421855728" Language="SFX" Streaming="true" Location="Loose">
					<ShortName>MUS_MainTown_Loop.wav</ShortName>
					<Path>Media/421855728.wem</Path>
					<CachePath>SFX/MUS_MainTown_Loop_D79FB2B7.wem</CachePath>
				</File>
				<File Id="440516985" Language="SFX" Streaming="true" Location="Loose">
					<ShortName>MUS_ForestBoss_Intro.wav</ShortName>
					<Path>Media/440516985.wem</Path>
					<CachePath>SFX/MUS_ForestBoss_Intro_D79FB2B7.wem</CachePath>
				</File>
				<File Id="728702870" Language="SFX" Streaming="true" Location="Loose">
					<ShortName>MUS_ForestBoss_Loop.wav</ShortName>
					<Path>Media/728702870.wem</Path>
					<CachePath>SFX/MUS_ForestBoss_Loop_D79FB2B7.wem</CachePath>
				</File>
				<File Id="919072691" Language="SFX" Streaming="true" Location="Loose">
					<ShortName>MUS_CastleEsterra.wav</ShortName>
					<Path>Media/919072691.wem</Path>
					<CachePath>SFX/MUS_CastleEsterra_D79FB2B7.wem</CachePath>
				</File>
				<File Id="937556372" Language="SFX" Streaming="true" Location="Loose">
					<ShortName>MUS_UndergroundForest_Loop.wav</ShortName>
					<Path>Media/937556372.wem</Path>
					<CachePath>SFX/MUS_UndergroundForest_Loop_D79FB2B7.wem</CachePath>
				</File>
				<File Id="976256781" Language="SFX" Streaming="true" Location="Loose">
					<ShortName>MUS_OverworldForest.wav</ShortName>
					<Path>Media/976256781.wem</Path>
					<CachePath>SFX/MUS_OverworldForest_D79FB2B7.wem</CachePath>
				</File>
			</Media>
			<Events>
				<Event Id="706813533" Name="Play_CastleEsterraMusic" DurationType="Infinite">
					<SwitchContainers>
						<SwitchContainer>
							<SwitchValue GroupType="State" GroupId="1106389198" Id="4293875712"/>
							<MediaRefs>
								<MediaRef Id="118347245"/>
							</MediaRefs>
						</SwitchContainer>
						<SwitchContainer>
							<SwitchValue GroupType="State" GroupId="1106389198" Id="387028970"/>
							<MediaRefs>
								<MediaRef Id="421855728"/>
							</MediaRefs>
						</SwitchContainer>
						<SwitchContainer>
							<SwitchValue GroupType="State" GroupId="1106389198" Id="1485340549"/>
							<MediaRefs>
								<MediaRef Id="146592704"/>
							</MediaRefs>
						</SwitchContainer>
						<SwitchContainer>
							<SwitchValue GroupType="State" GroupId="1106389198" Id="380412565"/>
							<MediaRefs>
								<MediaRef Id="919072691"/>
							</MediaRefs>
						</SwitchContainer>
						<SwitchContainer>
							<SwitchValue GroupType="State" GroupId="1106389198" Id="1984596375"/>
							<MediaRefs>
								<MediaRef Id="937556372"/>
							</MediaRefs>
						</SwitchContainer>
						<SwitchContainer>
							<SwitchValue GroupType="State" GroupId="1106389198" Id="2897915005"/>
							<MediaRefs>
								<MediaRef Id="374556251"/>
							</MediaRefs>
						</SwitchContainer>
						<SwitchContainer>
							<SwitchValue GroupType="State" GroupId="1106389198" Id="1906288962"/>
							<MediaRefs>
								<MediaRef Id="976256781"/>
							</MediaRefs>
						</SwitchContainer>
						<SwitchContainer>
							<SwitchValue GroupType="State" GroupId="1106389198" Id="949372955"/>
							<MediaRefs>
								<MediaRef Id="440516985"/>
								<MediaRef Id="728702870"/>
							</MediaRefs>
						</SwitchContainer>
					</SwitchContainers>
					<ActionSetState>
						<ActionSetStateEntry GroupId="1106389198" Id="380412565" Name="Music_CastleEsterra"/>
					</ActionSetState>
				</Event>
			</Events>
			<StateGroups>
				<StateGroup Id="1106389198" Name="PlayingSong">
					<States>
						<State Id="380412565" Name="Music_CastleEsterra"/>
						<State Id="387028970" Name="Music_MainTown"/>
						<State Id="748895195" Name="None"/>
						<State Id="949372955" Name="Music_ForestDungeonBoss"/>
						<State Id="1485340549" Name="Music_MainTheme"/>
						<State Id="1906288962" Name="Music_OverworldForest"/>
						<State Id="1984596375" Name="Music_UndergroundForest"/>
						<State Id="2897915005" Name="Music_GameOver"/>
						<State Id="4293875712" Name="Music_ForestDungeon"/>
					</States>
				</StateGroup>
			</StateGroups>
		</SoundBank>
		<SoundBank Id="2826179121" Type="User" Language="SFX" Hash="{811F3578-AF86-D040-B31B-FA4606C15EDE}">
			<ShortName>AMB_ForestDungeon</ShortName>
			<Path>AMB_ForestDungeon.bnk</Path>
			<Media>
				<File Id="733202127" Language="SFX" Streaming="false" Location="Memory">
					<ShortName>AMB_ForestDungeon.wav</ShortName>
					<CachePath>SFX/AMB_ForestDungeon_F9BF8FE5.wem</CachePath>
				</File>
			</Media>
			<Events>
				<Event Id="1858014972" Name="Play_ForestDungeon_AMB" DurationType="Infinite">
					<MediaRefs>
						<MediaRef Id="733202127"/>
					</MediaRefs>
				</Event>
			</Events>
		</SoundBank>
		<SoundBank Id="3253083610" Type="User" Language="SFX" Hash="{195A409E-199F-A3A7-857F-7CBA21EBE449}">
			<ShortName>SFX_Door_ForestDungeon_Close</ShortName>
			<Path>SFX_Door_ForestDungeon_Close.bnk</Path>
			<Media>
				<File Id="476682219" Language="SFX" Streaming="false" Location="Memory">
					<ShortName>SFX_BasicDoor_Close_01.wav</ShortName>
					<CachePath>SFX/SFX_BasicDoor_Close_01_10C4C929.wem</CachePath>
				</File>
			</Media>
			<Events>
				<Event Id="3406344955" Name="Play_ForestDungeon_BasicDoor_Close" DurationType="OneShot" DurationMin="1.120793" DurationMax="1.2595019">
					<MediaRefs>
						<MediaRef Id="476682219"/>
					</MediaRefs>
					<AuxBusRefs>
						<AuxBusRef Id="2137158287" Name="ForestDungeonVerb"/>
					</AuxBusRefs>
				</Event>
			</Events>
		</SoundBank>
		<SoundBank Id="3254244503" Type="User" Language="SFX" Hash="{BAE17744-CE96-569B-95A5-429E9BA47866}">
			<ShortName>MUS_ForestDungeonBoss</ShortName>
			<Path>MUS_ForestDungeonBoss.bnk</Path>
			<Media>
				<File Id="118347245" Language="SFX" Streaming="true" Location="Loose">
					<ShortName>MUS_ForestDungeon.wav</ShortName>
					<Path>Media/118347245.wem</Path>
					<CachePath>SFX/MUS_ForestDungeon_D79FB2B7.wem</CachePath>
				</File>
				<File Id="146592704" Language="SFX" Streaming="true" Location="Loose">
					<ShortName>MUS_MainTheme.wav</ShortName>
					<Path>Media/146592704.wem</Path>
					<CachePath>SFX/MUS_MainTheme_D79FB2B7.wem</CachePath>
				</File>
				<File Id="374556251" Language="SFX" Streaming="false" Location="Memory">
					<ShortName>MUS_GameOver_Jingle.wav</ShortName>
					<CachePath>SFX/MUS_GameOver_Jingle_D79FB2B7.wem</CachePath>
				</File>
				<File Id="421855728" Language="SFX" Streaming="true" Location="Loose">
					<ShortName>MUS_MainTown_Loop.wav</ShortName>
					<Path>Media/421855728.wem</Path>
					<CachePath>SFX/MUS_MainTown_Loop_D79FB2B7.wem</CachePath>
				</File>
				<File Id="440516985" Language="SFX" Streaming="true" Location="Loose">
					<ShortName>MUS_ForestBoss_Intro.wav</ShortName>
					<Path>Media/440516985.wem</Path>
					<CachePath>SFX/MUS_ForestBoss_Intro_D79FB2B7.wem</CachePath>
				</File>
				<File Id="728702870" Language="SFX" Streaming="true" Location="Loose">
					<ShortName>MUS_ForestBoss_Loop.wav</ShortName>
					<Path>Media/728702870.wem</Path>
					<CachePath>SFX/MUS_ForestBoss_Loop_D79FB2B7.wem</CachePath>
				</File>
				<File Id="919072691" Language="SFX" Streaming="true" Location="Loose">
					<ShortName>MUS_CastleEsterra.wav</ShortName>
					<Path>Media/919072691.wem</Path>
					<CachePath>SFX/MUS_CastleEsterra_D79FB2B7.wem</CachePath>
				</File>
				<File Id="937556372" Language="SFX" Streaming="true" Location="Loose">
					<ShortName>MUS_UndergroundForest_Loop.wav</ShortName>
					<Path>Media/937556372.wem</Path>
					<CachePath>SFX/MUS_UndergroundForest_Loop_D79FB2B7.wem</CachePath>
				</File>
				<File Id="976256781" Language="SFX" Streaming="true" Location="Loose">
					<ShortName>MUS_OverworldForest.wav</ShortName>
					<Path>Media/976256781.wem</Path>
					<CachePath>SFX/MUS_OverworldForest_D79FB2B7.wem</CachePath>
				</File>
			</Media>
			<Events>
				<Event Id="1007642718" Name="Play_ForestDungeonBoss" DurationType="Infinite">
					<SwitchContainers>
						<SwitchContainer>
							<SwitchValue GroupType="State" GroupId="1106389198" Id="4293875712"/>
							<MediaRefs>
								<MediaRef Id="118347245"/>
							</MediaRefs>
						</SwitchContainer>
						<SwitchContainer>
							<SwitchValue GroupType="State" GroupId="1106389198" Id="387028970"/>
							<MediaRefs>
								<MediaRef Id="421855728"/>
							</MediaRefs>
						</SwitchContainer>
						<SwitchContainer>
							<SwitchValue GroupType="State" GroupId="1106389198" Id="1485340549"/>
							<MediaRefs>
								<MediaRef Id="146592704"/>
							</MediaRefs>
						</SwitchContainer>
						<SwitchContainer>
							<SwitchValue GroupType="State" GroupId="1106389198" Id="380412565"/>
							<MediaRefs>
								<MediaRef Id="919072691"/>
							</MediaRefs>
						</SwitchContainer>
						<SwitchContainer>
							<SwitchValue GroupType="State" GroupId="1106389198" Id="1984596375"/>
							<MediaRefs>
								<MediaRef Id="937556372"/>
							</MediaRefs>
						</SwitchContainer>
						<SwitchContainer>
							<SwitchValue GroupType="State" GroupId="1106389198" Id="2897915005"/>
							<MediaRefs>
								<MediaRef Id="374556251"/>
							</MediaRefs>
						</SwitchContainer>
						<SwitchContainer>
							<SwitchValue GroupType="State" GroupId="1106389198" Id="1906288962"/>
							<MediaRefs>
								<MediaRef Id="976256781"/>
							</MediaRefs>
						</SwitchContainer>
						<SwitchContainer>
							<SwitchValue GroupType="State" GroupId="1106389198" Id="949372955"/>
							<MediaRefs>
								<MediaRef Id="440516985"/>
								<MediaRef Id="728702870"/>
							</MediaRefs>
						</SwitchContainer>
					</SwitchContainers>
					<ActionSetState>
						<ActionSetStateEntry GroupId="1106389198" Id="949372955" Name="Music_ForestDungeonBoss"/>
					</ActionSetState>
				</Event>
			</Events>
			<StateGroups>
				<StateGroup Id="1106389198" Name="PlayingSong">
					<States>
						<State Id="380412565" Name="Music_CastleEsterra"/>
						<State Id="387028970" Name="Music_MainTown"/>
						<State Id="748895195" Name="None"/>
						<State Id="949372955" Name="Music_ForestDungeonBoss"/>
						<State Id="1485340549" Name="Music_MainTheme"/>
						<State Id="1906288962" Name="Music_OverworldForest"/>
						<State Id="1984596375" Name="Music_UndergroundForest"/>
						<State Id="2897915005" Name="Music_GameOver"/>
						<State Id="4293875712" Name="Music_ForestDungeon"/>
					</States>
				</StateGroup>
			</StateGroups>
		</SoundBank>
		<SoundBank Id="3413408933" Type="User" Language="SFX" Hash="{A30E7917-403A-54B0-7D2C-BA023021F03B}">
			<ShortName>MUS_TitleScreen</ShortName>
			<Path>MUS_TitleScreen.bnk</Path>
			<Media>
				<File Id="118347245" Language="SFX" Streaming="true" Location="Loose">
					<ShortName>MUS_ForestDungeon.wav</ShortName>
					<Path>Media/118347245.wem</Path>
					<CachePath>SFX/MUS_ForestDungeon_D79FB2B7.wem</CachePath>
				</File>
				<File Id="146592704" Language="SFX" Streaming="true" Location="Loose">
					<ShortName>MUS_MainTheme.wav</ShortName>
					<Path>Media/146592704.wem</Path>
					<CachePath>SFX/MUS_MainTheme_D79FB2B7.wem</CachePath>
				</File>
				<File Id="374556251" Language="SFX" Streaming="false" Location="Memory">
					<ShortName>MUS_GameOver_Jingle.wav</ShortName>
					<CachePath>SFX/MUS_GameOver_Jingle_D79FB2B7.wem</CachePath>
				</File>
				<File Id="421855728" Language="SFX" Streaming="true" Location="Loose">
					<ShortName>MUS_MainTown_Loop.wav</ShortName>
					<Path>Media/421855728.wem</Path>
					<CachePath>SFX/MUS_MainTown_Loop_D79FB2B7.wem</CachePath>
				</File>
				<File Id="440516985" Language="SFX" Streaming="true" Location="Loose">
					<ShortName>MUS_ForestBoss_Intro.wav</ShortName>
					<Path>Media/440516985.wem</Path>
					<CachePath>SFX/MUS_ForestBoss_Intro_D79FB2B7.wem</CachePath>
				</File>
				<File Id="728702870" Language="SFX" Streaming="true" Location="Loose">
					<ShortName>MUS_ForestBoss_Loop.wav</ShortName>
					<Path>Media/728702870.wem</Path>
					<CachePath>SFX/MUS_ForestBoss_Loop_D79FB2B7.wem</CachePath>
				</File>
				<File Id="919072691" Language="SFX" Streaming="true" Location="Loose">
					<ShortName>MUS_CastleEsterra.wav</ShortName>
					<Path>Media/919072691.wem</Path>
					<CachePath>SFX/MUS_CastleEsterra_D79FB2B7.wem</CachePath>
				</File>
				<File Id="937556372" Language="SFX" Streaming="true" Location="Loose">
					<ShortName>MUS_UndergroundForest_Loop.wav</ShortName>
					<Path>Media/937556372.wem</Path>
					<CachePath>SFX/MUS_UndergroundForest_Loop_D79FB2B7.wem</CachePath>
				</File>
				<File Id="976256781" Language="SFX" Streaming="true" Location="Loose">
					<ShortName>MUS_OverworldForest.wav</ShortName>
					<Path>Media/976256781.wem</Path>
					<CachePath>SFX/MUS_OverworldForest_D79FB2B7.wem</CachePath>
				</File>
			</Media>
			<Events>
				<Event Id="4182175493" Name="Play_TitleScreenMusic" DurationType="Infinite">
					<SwitchContainers>
						<SwitchContainer>
							<SwitchValue GroupType="State" GroupId="1106389198" Id="4293875712"/>
							<MediaRefs>
								<MediaRef Id="118347245"/>
							</MediaRefs>
						</SwitchContainer>
						<SwitchContainer>
							<SwitchValue GroupType="State" GroupId="1106389198" Id="387028970"/>
							<MediaRefs>
								<MediaRef Id="421855728"/>
							</MediaRefs>
						</SwitchContainer>
						<SwitchContainer>
							<SwitchValue GroupType="State" GroupId="1106389198" Id="1485340549"/>
							<MediaRefs>
								<MediaRef Id="146592704"/>
							</MediaRefs>
						</SwitchContainer>
						<SwitchContainer>
							<SwitchValue GroupType="State" GroupId="1106389198" Id="380412565"/>
							<MediaRefs>
								<MediaRef Id="919072691"/>
							</MediaRefs>
						</SwitchContainer>
						<SwitchContainer>
							<SwitchValue GroupType="State" GroupId="1106389198" Id="1984596375"/>
							<MediaRefs>
								<MediaRef Id="937556372"/>
							</MediaRefs>
						</SwitchContainer>
						<SwitchContainer>
							<SwitchValue GroupType="State" GroupId="1106389198" Id="2897915005"/>
							<MediaRefs>
								<MediaRef Id="374556251"/>
							</MediaRefs>
						</SwitchContainer>
						<SwitchContainer>
							<SwitchValue GroupType="State" GroupId="1106389198" Id="1906288962"/>
							<MediaRefs>
								<MediaRef Id="976256781"/>
							</MediaRefs>
						</SwitchContainer>
						<SwitchContainer>
							<SwitchValue GroupType="State" GroupId="1106389198" Id="949372955"/>
							<MediaRefs>
								<MediaRef Id="440516985"/>
								<MediaRef Id="728702870"/>
							</MediaRefs>
						</SwitchContainer>
					</SwitchContainers>
					<ActionSetState>
						<ActionSetStateEntry GroupId="1106389198" Id="1485340549" Name="Music_MainTheme"/>
					</ActionSetState>
				</Event>
			</Events>
			<StateGroups>
				<StateGroup Id="1106389198" Name="PlayingSong">
					<States>
						<State Id="380412565" Name="Music_CastleEsterra"/>
						<State Id="387028970" Name="Music_MainTown"/>
						<State Id="748895195" Name="None"/>
						<State Id="949372955" Name="Music_ForestDungeonBoss"/>
						<State Id="1485340549" Name="Music_MainTheme"/>
						<State Id="1906288962" Name="Music_OverworldForest"/>
						<State Id="1984596375" Name="Music_UndergroundForest"/>
						<State Id="2897915005" Name="Music_GameOver"/>
						<State Id="4293875712" Name="Music_ForestDungeon"/>
					</States>
				</StateGroup>
			</StateGroups>
		</SoundBank>
		<SoundBank Id="3589812408" Type="User" Language="SFX" Hash="{1DB0DFF0-AF08-D399-802D-5D8DF58D3FA0}">
			<ShortName>Music_Soundbank</ShortName>
			<Path>Music_Soundbank.bnk</Path>
			<Media>
				<File Id="118347245" Language="SFX" Streaming="true" Location="Loose">
					<ShortName>MUS_ForestDungeon.wav</ShortName>
					<Path>Media/118347245.wem</Path>
					<CachePath>SFX/MUS_ForestDungeon_D79FB2B7.wem</CachePath>
				</File>
				<File Id="146592704" Language="SFX" Streaming="true" Location="Loose">
					<ShortName>MUS_MainTheme.wav</ShortName>
					<Path>Media/146592704.wem</Path>
					<CachePath>SFX/MUS_MainTheme_D79FB2B7.wem</CachePath>
				</File>
				<File Id="374556251" Language="SFX" Streaming="false" Location="Memory">
					<ShortName>MUS_GameOver_Jingle.wav</ShortName>
					<CachePath>SFX/MUS_GameOver_Jingle_D79FB2B7.wem</CachePath>
				</File>
				<File Id="421855728" Language="SFX" Streaming="true" Location="Loose">
					<ShortName>MUS_MainTown_Loop.wav</ShortName>
					<Path>Media/421855728.wem</Path>
					<CachePath>SFX/MUS_MainTown_Loop_D79FB2B7.wem</CachePath>
				</File>
				<File Id="440516985" Language="SFX" Streaming="true" Location="Loose">
					<ShortName>MUS_ForestBoss_Intro.wav</ShortName>
					<Path>Media/440516985.wem</Path>
					<CachePath>SFX/MUS_ForestBoss_Intro_D79FB2B7.wem</CachePath>
				</File>
				<File Id="728702870" Language="SFX" Streaming="true" Location="Loose">
					<ShortName>MUS_ForestBoss_Loop.wav</ShortName>
					<Path>Media/728702870.wem</Path>
					<CachePath>SFX/MUS_ForestBoss_Loop_D79FB2B7.wem</CachePath>
				</File>
				<File Id="919072691" Language="SFX" Streaming="true" Location="Loose">
					<ShortName>MUS_CastleEsterra.wav</ShortName>
					<Path>Media/919072691.wem</Path>
					<CachePath>SFX/MUS_CastleEsterra_D79FB2B7.wem</CachePath>
				</File>
				<File Id="937556372" Language="SFX" Streaming="true" Location="Loose">
					<ShortName>MUS_UndergroundForest_Loop.wav</ShortName>
					<Path>Media/937556372.wem</Path>
					<CachePath>SFX/MUS_UndergroundForest_Loop_D79FB2B7.wem</CachePath>
				</File>
				<File Id="976256781" Language="SFX" Streaming="true" Location="Loose">
					<ShortName>MUS_OverworldForest.wav</ShortName>
					<Path>Media/976256781.wem</Path>
					<CachePath>SFX/MUS_OverworldForest_D79FB2B7.wem</CachePath>
				</File>
			</Media>
			<Events>
				<Event Id="2932040671" Name="Play_Music" DurationType="Infinite">
					<SwitchContainers>
						<SwitchContainer>
							<SwitchValue GroupType="State" GroupId="1106389198" Id="4293875712"/>
							<MediaRefs>
								<MediaRef Id="118347245"/>
							</MediaRefs>
						</SwitchContainer>
						<SwitchContainer>
							<SwitchValue GroupType="State" GroupId="1106389198" Id="387028970"/>
							<MediaRefs>
								<MediaRef Id="421855728"/>
							</MediaRefs>
						</SwitchContainer>
						<SwitchContainer>
							<SwitchValue GroupType="State" GroupId="1106389198" Id="1485340549"/>
							<MediaRefs>
								<MediaRef Id="146592704"/>
							</MediaRefs>
						</SwitchContainer>
						<SwitchContainer>
							<SwitchValue GroupType="State" GroupId="1106389198" Id="380412565"/>
							<MediaRefs>
								<MediaRef Id="919072691"/>
							</MediaRefs>
						</SwitchContainer>
						<SwitchContainer>
							<SwitchValue GroupType="State" GroupId="1106389198" Id="1984596375"/>
							<MediaRefs>
								<MediaRef Id="937556372"/>
							</MediaRefs>
						</SwitchContainer>
						<SwitchContainer>
							<SwitchValue GroupType="State" GroupId="1106389198" Id="2897915005"/>
							<MediaRefs>
								<MediaRef Id="374556251"/>
							</MediaRefs>
						</SwitchContainer>
						<SwitchContainer>
							<SwitchValue GroupType="State" GroupId="1106389198" Id="1906288962"/>
							<MediaRefs>
								<MediaRef Id="976256781"/>
							</MediaRefs>
						</SwitchContainer>
						<SwitchContainer>
							<SwitchValue GroupType="State" GroupId="1106389198" Id="949372955"/>
							<MediaRefs>
								<MediaRef Id="440516985"/>
								<MediaRef Id="728702870"/>
							</MediaRefs>
						</SwitchContainer>
					</SwitchContainers>
				</Event>
			</Events>
			<StateGroups>
				<StateGroup Id="1106389198" Name="PlayingSong">
					<States>
						<State Id="380412565" Name="Music_CastleEsterra"/>
						<State Id="387028970" Name="Music_MainTown"/>
						<State Id="748895195" Name="None"/>
						<State Id="949372955" Name="Music_ForestDungeonBoss"/>
						<State Id="1485340549" Name="Music_MainTheme"/>
						<State Id="1906288962" Name="Music_OverworldForest"/>
						<State Id="1984596375" Name="Music_UndergroundForest"/>
						<State Id="2897915005" Name="Music_GameOver"/>
						<State Id="4293875712" Name="Music_ForestDungeon"/>
					</States>
				</StateGroup>
			</StateGroups>
		</SoundBank>
		<SoundBank Id="3591353126" Type="User" Language="SFX" Hash="{99461B64-20E1-8373-01AF-6BBA1D11C2F7}">
			<ShortName>MUS_OverworldForest</ShortName>
			<Path>MUS_OverworldForest.bnk</Path>
			<Media>
				<File Id="118347245" Language="SFX" Streaming="true" Location="Loose">
					<ShortName>MUS_ForestDungeon.wav</ShortName>
					<Path>Media/118347245.wem</Path>
					<CachePath>SFX/MUS_ForestDungeon_D79FB2B7.wem</CachePath>
				</File>
				<File Id="146592704" Language="SFX" Streaming="true" Location="Loose">
					<ShortName>MUS_MainTheme.wav</ShortName>
					<Path>Media/146592704.wem</Path>
					<CachePath>SFX/MUS_MainTheme_D79FB2B7.wem</CachePath>
				</File>
				<File Id="374556251" Language="SFX" Streaming="false" Location="Memory">
					<ShortName>MUS_GameOver_Jingle.wav</ShortName>
					<CachePath>SFX/MUS_GameOver_Jingle_D79FB2B7.wem</CachePath>
				</File>
				<File Id="421855728" Language="SFX" Streaming="true" Location="Loose">
					<ShortName>MUS_MainTown_Loop.wav</ShortName>
					<Path>Media/421855728.wem</Path>
					<CachePath>SFX/MUS_MainTown_Loop_D79FB2B7.wem</CachePath>
				</File>
				<File Id="440516985" Language="SFX" Streaming="true" Location="Loose">
					<ShortName>MUS_ForestBoss_Intro.wav</ShortName>
					<Path>Media/440516985.wem</Path>
					<CachePath>SFX/MUS_ForestBoss_Intro_D79FB2B7.wem</CachePath>
				</File>
				<File Id="728702870" Language="SFX" Streaming="true" Location="Loose">
					<ShortName>MUS_ForestBoss_Loop.wav</ShortName>
					<Path>Media/728702870.wem</Path>
					<CachePath>SFX/MUS_ForestBoss_Loop_D79FB2B7.wem</CachePath>
				</File>
				<File Id="919072691" Language="SFX" Streaming="true" Location="Loose">
					<ShortName>MUS_CastleEsterra.wav</ShortName>
					<Path>Media/919072691.wem</Path>
					<CachePath>SFX/MUS_CastleEsterra_D79FB2B7.wem</CachePath>
				</File>
				<File Id="937556372" Language="SFX" Streaming="true" Location="Loose">
					<ShortName>MUS_UndergroundForest_Loop.wav</ShortName>
					<Path>Media/937556372.wem</Path>
					<CachePath>SFX/MUS_UndergroundForest_Loop_D79FB2B7.wem</CachePath>
				</File>
				<File Id="976256781" Language="SFX" Streaming="true" Location="Loose">
					<ShortName>MUS_OverworldForest.wav</ShortName>
					<Path>Media/976256781.wem</Path>
					<CachePath>SFX/MUS_OverworldForest_D79FB2B7.wem</CachePath>
				</File>
			</Media>
			<Events>
				<Event Id="693146296" Name="Play_OverworldForestMusic" DurationType="Infinite">
					<SwitchContainers>
						<SwitchContainer>
							<SwitchValue GroupType="State" GroupId="1106389198" Id="4293875712"/>
							<MediaRefs>
								<MediaRef Id="118347245"/>
							</MediaRefs>
						</SwitchContainer>
						<SwitchContainer>
							<SwitchValue GroupType="State" GroupId="1106389198" Id="387028970"/>
							<MediaRefs>
								<MediaRef Id="421855728"/>
							</MediaRefs>
						</SwitchContainer>
						<SwitchContainer>
							<SwitchValue GroupType="State" GroupId="1106389198" Id="1485340549"/>
							<MediaRefs>
								<MediaRef Id="146592704"/>
							</MediaRefs>
						</SwitchContainer>
						<SwitchContainer>
							<SwitchValue GroupType="State" GroupId="1106389198" Id="380412565"/>
							<MediaRefs>
								<MediaRef Id="919072691"/>
							</MediaRefs>
						</SwitchContainer>
						<SwitchContainer>
							<SwitchValue GroupType="State" GroupId="1106389198" Id="1984596375"/>
							<MediaRefs>
								<MediaRef Id="937556372"/>
							</MediaRefs>
						</SwitchContainer>
						<SwitchContainer>
							<SwitchValue GroupType="State" GroupId="1106389198" Id="2897915005"/>
							<MediaRefs>
								<MediaRef Id="374556251"/>
							</MediaRefs>
						</SwitchContainer>
						<SwitchContainer>
							<SwitchValue GroupType="State" GroupId="1106389198" Id="1906288962"/>
							<MediaRefs>
								<MediaRef Id="976256781"/>
							</MediaRefs>
						</SwitchContainer>
						<SwitchContainer>
							<SwitchValue GroupType="State" GroupId="1106389198" Id="949372955"/>
							<MediaRefs>
								<MediaRef Id="440516985"/>
								<MediaRef Id="728702870"/>
							</MediaRefs>
						</SwitchContainer>
					</SwitchContainers>
					<ActionSetState>
						<ActionSetStateEntry GroupId="1106389198" Id="1906288962" Name="Music_OverworldForest"/>
					</ActionSetState>
				</Event>
			</Events>
			<StateGroups>
				<StateGroup Id="1106389198" Name="PlayingSong">
					<States>
						<State Id="380412565" Name="Music_CastleEsterra"/>
						<State Id="387028970" Name="Music_MainTown"/>
						<State Id="748895195" Name="None"/>
						<State Id="949372955" Name="Music_ForestDungeonBoss"/>
						<State Id="1485340549" Name="Music_MainTheme"/>
						<State Id="1906288962" Name="Music_OverworldForest"/>
						<State Id="1984596375" Name="Music_UndergroundForest"/>
						<State Id="2897915005" Name="Music_GameOver"/>
						<State Id="4293875712" Name="Music_ForestDungeon"/>
					</States>
				</StateGroup>
			</StateGroups>
		</SoundBank>
		<SoundBank Id="3825749273" Type="User" Language="SFX" Hash="{BBD7BC5B-2ED7-F4DB-8ABF-2437140034A4}">
			<ShortName>SFX_Crystal</ShortName>
			<Path>SFX_Crystal.bnk</Path>
			<Media>
				<File Id="836849017" Language="SFX" Streaming="false" Location="Memory">
					<ShortName>SFX_Crystal_Activate.wav</ShortName>
					<CachePath>SFX/SFX_Crystal_Activate_10C4C929.wem</CachePath>
				</File>
			</Media>
			<Events>
				<Event Id="4074254608" Name="Play_Crystal_Activate" DurationType="OneShot" DurationMin="1.5222708" DurationMax="1.5222708">
					<MediaRefs>
						<MediaRef Id="836849017"/>
					</MediaRefs>
				</Event>
			</Events>
		</SoundBank>
	</SoundBanks>
	<FileHash>{4D1FBEE1-9FE2-DFEA-CA4B-D754A762527D}</FileHash>
</SoundBanksInfo>
